{
"type": "FeatureCollection",
"name": "AndereHTWStandorte_6",
"crs": { "type": "name", "properties": { "name": "urn:ogc:def:crs:OGC:1.3:CRS84" } },
"features": [
{ "type": "Feature", "properties": { "id": 2, "Standort": "Rotenbühl" }, "geometry": { "type": "Point", "coordinates": [ 7.015068612897803, 49.243324796215589 ] } },
{ "type": "Feature", "properties": { "id": 4, "Standort": "Alt-Saarbrücken" }, "geometry": { "type": "Point", "coordinates": [ 6.974044047778766, 49.235644446729559 ] } },
{ "type": "Feature", "properties": { "id": 1, "Standort": "Göttelborn" }, "geometry": { "type": "Point", "coordinates": [ 7.034626162982767, 49.343353779799308 ] } }
]
}
