{
"type": "FeatureCollection",
"name": "Bahnhfe_4",
"crs": { "type": "name", "properties": { "name": "urn:ogc:def:crs:OGC:1.3:CRS84" } },
"features": [
{ "type": "Feature", "properties": { "full_id": "n5063120722", "name": "Saarbrücken-Burbach Mitte" }, "geometry": { "type": "Point", "coordinates": [ 6.9445794, 49.2436268 ] } }
]
}
